latex_process/__init__.py
latex_process/processor.py
latex_process/plugins/example_plugin.py
latex_process-0.1.2.dist-info/LICENSE
latex_process-0.1.2.dist-info/METADATA
latex_process-0.1.2.dist-info/WHEEL
latex_process-0.1.2.dist-info/entry_points.txt
latex_process-0.1.2.dist-info/top_level.txt
latex_process-0.1.2.dist-info/RECORD
