Metadata-Version: 2.2
Name: latex-process
Version: 0.1.2
Summary: Ultimate LaTeX Processing Tool
Home-page: https://github.com/fenilsonani/latex-process
Author: Fenil Sonani
Author-email: contact@fenilsonani.com
License: MIT
Classifier: Programming Language :: Python :: 3
Classifier: License :: OSI Approved :: MIT License
Classifier: Operating System :: OS Independent
Requires-Python: >=3.7
License-File: LICENSE
Requires-Dist: jinja2>=3.0
Requires-Dist: rich>=12.0
Requires-Dist: watchdog>=2.0
Requires-Dist: pandoc>=2.0
